pyclimenu/__init__.py
pyclimenu/colors.py
pyclimenu/menu.py
pyclimenu-0.1.18.dist-info/LICENSE.txt
pyclimenu-0.1.18.dist-info/METADATA
pyclimenu-0.1.18.dist-info/WHEEL
pyclimenu-0.1.18.dist-info/top_level.txt
pyclimenu-0.1.18.dist-info/RECORD
